osdk/__init__.py
osdk/__main__.py
osdk/args.py
osdk/builder.py
osdk/cmds.py
osdk/const.py
osdk/context.py
osdk/graph.py
osdk/jexpr.py
osdk/logger.py
osdk/mixins.py
osdk/model.py
osdk/ninja.py
osdk/plugins.py
osdk/rules.py
osdk/shell.py
osdk/utils.py
osdk/vt100.py
osdk-31196382.dist-info/LICENSE
osdk-31196382.dist-info/METADATA
osdk-31196382.dist-info/WHEEL
osdk-31196382.dist-info/entry_points.txt
osdk-31196382.dist-info/top_level.txt
osdk-31196382.dist-info/RECORD
