Metadata-Version: 2.1
Name: osdk
Version: 31196382
Summary: Operating System Development Kit
Home-page: https://devse.wiki/
Author: The DEVSE Community
Author-email: contact@devse.wiki
License: MIT
Platform: any
Requires-Python: >=3.10
License-File: LICENSE
Requires-Dist: graphviz
Requires-Dist: requests
